[
  {
    "adu": "N",
    "application_submission_method": "in-house",
    "block": "0576",
    "data_as_of": "2025-07-01T23:55:01.000",
    "data_loaded_at": "2025-07-02T03:38:58.795",
    "description": "install errcs",
    "estimated_cost": "5000.0",
    "existing_construction_type": "1",
    "existing_construction_type_description": "constr type 1",
    "existing_occupancy": "R-2",
    "existing_units": "72.0",
    "existing_use": "apartments",
    "filed_date": "2025-07-01T20:07:56.000",
    "fire_only_permit": "Y",
    "last_permit_activity_date": "2025-07-01T15:49:37.000",
    "location": {
      "type": "Point",
      "coordinates": [
        -122.425228349,
        37.794820083
      ]
    },
    "lot": "026",
    "neighborhoods_analysis_boundaries": "Pacific Heights",
    "number_of_existing_stories": "7",
    "number_of_proposed_stories": "7",
    "permit_creation_date": "2025-07-01T20:07:56.000",
    "permit_number": "202506309745",
    "permit_type": "3",
    "permit_type_definition": "additions alterations or repairs",
    "plansets": "2",
    "point_source": "eas_address_point",
    "primary_address_flag": "Y",
    "proposed_construction_type": "1",
    "proposed_construction_type_description": "constr type 1",
    "proposed_occupancy": "R-2",
    "proposed_units": "72.0",
    "proposed_use": "apartments",
    "record_id": "172534175024",
    "status": "filed",
    "status_date": "2025-07-01T20:07:56.000",
    "street_name": "Pacific",
    "street_number": "1800",
    "street_suffix": "Av",
    "supervisor_district": "2",
    "zipcode": "94109"
  },
  {
    "adu": "N",
    "application_submission_method": "website",
    "block": "0275B",
    "data_as_of": "2025-07-01T23:55:01.000",
    "data_loaded_at": "2025-07-02T03:38:58.795",
    "description": "in-kind remodeling of 1 kitchen(s) in 3rd fl and in-kind remodeling of 2 bathroom(s) in 3rd fl with 0 shower pan(s).",
    "estimated_cost": "31600.0",
    "existing_construction_type": "3",
    "existing_construction_type_description": "constr type 3",
    "existing_occupancy": "R-3",
    "existing_units": "1.0",
    "existing_use": "1 family dwelling",
    "filed_date": "2025-07-01T17:08:36.000",
    "issued_date": "2025-07-01T17:12:25.000",
    "last_permit_activity_date": "2025-07-01T17:08:36.000",
    "location": {
      "type": "Point",
      "coordinates": [
        -122.412562004,
        37.789826424
      ]
    },
    "lot": "054",
    "neighborhoods_analysis_boundaries": "Nob Hill",
    "number_of_existing_stories": "0",
    "number_of_proposed_stories": "0",
    "permit_creation_date": "2025-07-01T17:08:35.000",
    "permit_number": "202507019984",
    "permit_type": "8",
    "permit_type_definition": "otc alterations permit",
    "plansets": "0",
    "point_source": "eas_address_point",
    "primary_address_flag": "Y",
    "proposed_construction_type": "3",
    "proposed_construction_type_description": "constr type 3",
    "proposed_occupancy": "R-3",
    "proposed_units": "1.0",
    "proposed_use": "1 family dwelling",
    "record_id": "172559566552",
    "revised_cost": "31600.0",
    "status": "issued",
    "status_date": "2025-07-01T17:12:25.000",
    "street_name": "Bush",
    "street_number": "900",
    "street_suffix": "St",
    "supervisor_district": "3",
    "unit": "314",
    "zipcode": "94109"
  },
  {
    "adu": "N",
    "application_submission_method": "website",
    "block": "1842",
    "data_as_of": "2025-07-01T23:55:01.000",
    "data_loaded_at": "2025-07-02T03:38:58.795",
    "description": "in-kind remodeling of 1 kitchen(s) in 1st fl",
    "estimated_cost": "40000.0",
    "existing_construction_type": "5",
    "existing_construction_type_description": "wood frame (5)",
    "existing_occupancy": "R-3",
    "existing_units": "2.0",
    "existing_use": "2 family dwelling",
    "filed_date": "2025-07-01T16:42:53.000",
    "issued_date": "2025-07-01T16:43:57.000",
    "last_permit_activity_date": "2025-07-01T16:42:53.000",
    "location": {
      "type": "Point",
      "coordinates": [
        -122.468829747,
        37.760437086
      ]
    },
    "lot": "022",
    "neighborhoods_analysis_boundaries": "Inner Sunset",
    "number_of_existing_stories": "3",
    "number_of_proposed_stories": "3",
    "permit_creation_date": "2025-07-01T16:42:53.000",
    "permit_number": "202507019983",
    "permit_type": "8",
    "permit_type_definition": "otc alterations permit",
    "plansets": "0",
    "point_source": "eas_address_point",
    "primary_address_flag": "Y",
    "proposed_construction_type": "5",
    "proposed_construction_type_description": "wood frame (5)",
    "proposed_occupancy": "R-3",
    "proposed_units": "2.0",
    "proposed_use": "2 family dwelling",
    "record_id": "1725591116882",
    "revised_cost": "40000.0",
    "status": "issued",
    "status_date": "2025-07-01T16:43:57.000",
    "street_name": "Kirkham",
    "street_number": "736",
    "street_suffix": "St",
    "supervisor_district": "7",
    "zipcode": "94122"
  }
]
